djangoldp_project/__init__.py
djangoldp_project/admin.py
djangoldp_project/apps.py
djangoldp_project/check_integrity.py
djangoldp_project/djangoldp_urls.py
djangoldp_project/factories.py
djangoldp_project/models.py
djangoldp_project/settings.py
djangoldp_project/views.py
djangoldp_project/management/__init__.py
djangoldp_project/management/commands/__init__.py
djangoldp_project/management/commands/mock_project.py
djangoldp_project/migrations/0001_initial.py
djangoldp_project/migrations/0002_member_is_admin.py
djangoldp_project/migrations/0003_auto_20191209_1712.py
djangoldp_project/migrations/0004_auto_20191211_1552.py
djangoldp_project/migrations/0005_auto_20191217_1301.py
djangoldp_project/migrations/0006_auto_20200114_1547.py
djangoldp_project/migrations/0007_customer_owner.py
djangoldp_project/migrations/0008_auto_20200326_2132.py
djangoldp_project/migrations/0009_project_status.py
djangoldp_project/migrations/0010_auto_20200522_1516.py
djangoldp_project/migrations/0011_remove_member_name.py
djangoldp_project/migrations/0012_auto_20200610_1323.py
djangoldp_project/migrations/0013_auto_20200619_0808.py
djangoldp_project/migrations/0014_auto_20200903_1051.py
djangoldp_project/migrations/0015_auto_20200926_0911.py
djangoldp_project/migrations/0016_remove_project_team.py
djangoldp_project/migrations/0017_auto_20210125_1847.py
djangoldp_project/migrations/0018_auto_20210504_1748.py
djangoldp_project/migrations/0019_auto_20210519_1349.py
djangoldp_project/migrations/0020_auto_20210520_2005.py
djangoldp_project/migrations/0021_auto_20210521_1202.py
djangoldp_project/migrations/0022_alter_customer_options_alter_project_options.py
djangoldp_project/migrations/0023_alter_businessprovider_options_and_more.py
djangoldp_project/migrations/0024_auto_20231013_1440.py
djangoldp_project/migrations/0025_add_timestamps_to_models.py
djangoldp_project/migrations/__init__.py
djangoldp_project/tests/__init__.py
djangoldp_project/tests/runner.py
djangoldp_project-6.0.0.dist-info/METADATA
djangoldp_project-6.0.0.dist-info/WHEEL
djangoldp_project-6.0.0.dist-info/top_level.txt
djangoldp_project-6.0.0.dist-info/RECORD
